borfile/__init__.py
borfile/cli.py
borfile/codes.py
borfile/file.py
borfile/utils.py
borfile-0.2.1.dist-info/entry_points.txt
borfile-0.2.1.dist-info/licenses/LICENSE
borfile-0.2.1.dist-info/WHEEL
borfile-0.2.1.dist-info/METADATA
borfile-0.2.1.dist-info/RECORD
