Metadata-Version: 2.4
Name: borfile
Version: 0.2.1
Summary: Small Python library to manipulate BOR files.
Author-email: Salem Harrache <dev@mail.lim.eu>
Requires-Python: >=3.9
Classifier: Development Status :: 2 - Pre-Alpha
Classifier: License :: OSI Approved :: MIT License
Classifier: Programming Language :: Python :: 3
Classifier: Programming Language :: Python :: 3.9
Classifier: Programming Language :: Python :: 3.10
Classifier: Programming Language :: Python :: 3.11
Classifier: Programming Language :: Python :: 3.12
License-File: LICENSE
Requires-Dist: click
Requires-Dist: xarray
Requires-Dist: scipy
Requires-Dist: xmltodict
Requires-Dist: stream-zip
Requires-Dist: black ; extra == "dev"
Requires-Dist: bump-my-version ; extra == "dev"
Requires-Dist: ruff ; extra == "dev"
Requires-Dist: isort ; extra == "dev"
Requires-Dist: jedi ; extra == "dev"
Requires-Dist: pdbpp ; extra == "dev"
Requires-Dist: lxml ; extra == "extra"
Requires-Dist: pyarrow ; extra == "extra"
Requires-Dist: zarr ; extra == "extra"
Requires-Dist: jupyterlab ; extra == "plot"
Requires-Dist: matplotlib ; extra == "plot"
Requires-Dist: coverage ; extra == "test"
Requires-Dist: pytest ; extra == "test"
Requires-Dist: pytest-cases ; extra == "test"
Requires-Dist: pytest-cov ; extra == "test"
Requires-Dist: pytest-datafiles ; extra == "test"
Requires-Dist: pytest-sugar ; extra == "test"
Project-URL: Changes, https://github.com/LIMSAS/borfile/blob/master/CHANGES.rst
Project-URL: Home, https://bor-form.at
Project-URL: Source, https://github.com/LIMSAS/borfile
Provides-Extra: dev
Provides-Extra: extra
Provides-Extra: plot
Provides-Extra: test
